README.md
setup.cfg
setup.py
Makechr.egg-info/PKG-INFO
Makechr.egg-info/SOURCES.txt
Makechr.egg-info/dependency_links.txt
Makechr.egg-info/requires.txt
Makechr.egg-info/top_level.txt
bin/makechr
makechr/__init__.py
makechr/app.py
makechr/bg_color_spec.py
makechr/binary_file_writer.py
makechr/chr_data.py
makechr/color_cycler.py
makechr/constants.py
makechr/data.py
makechr/decompose_sprites_processor.py
makechr/direction_constants.py
makechr/eight_by_sixteen_processor.py
makechr/errors.py
makechr/extract_indexed_image_palette.py
makechr/file_modify_watcher.py
makechr/free_sprite_processor.py
makechr/geometry.py
makechr/guess_best_palette.py
makechr/gui.py
makechr/id_manifest.py
makechr/image_processor.py
makechr/makechr.py
makechr/makepal_processor.py
makechr/memory_importer.py
makechr/num_range.py
makechr/object_file_writer.py
makechr/outline_tracer.py
makechr/palette.py
makechr/partitions.py
makechr/pixel_art_renderer.py
makechr/ppu_memory.py
makechr/rectilinear_coverage.py
makechr/region_perimeter.py
makechr/rgb.py
makechr/rgb_almighty.py
makechr/rgb_fceux.py
makechr/rgb_nesst.py
makechr/rom_builder.py
makechr/span_list_delta.py
makechr/view_renderer.py
makechr/wrapped_image_palette.py
makechr/gen/__init__.py
makechr/gen/valiant_pb2.py
makechr/res/icon.png
makechr/res/nt_font.png
makechr/res/nt_tiny.png
makechr/res/perf_data.png
makechr/res/reuse-key.png
makechr/res/systemcolors.png
makechr/res/windows.ico