Metadata-Version: 2.3
Name: makechr
Version: 1.8.5
Summary: Graphics Tool for Retro Image Formats
Project-URL: Homepage, https://dustmop.io/software/makechr
Project-URL: Issues, https://github.com/dustmop/makechr/issues
Author-email: Dustin Long <me@dustmop.io>
License: GPL3 License
License-File: LICENSE.txt
Classifier: Operating System :: OS Independent
Classifier: Programming Language :: Python :: 3
Requires-Python: >=3.8
Requires-Dist: pillow
Requires-Dist: protobuf
